{"url":"https:\/\/b24-ktafz3.bitrix24.ru\/rest\/profile.json","info":{"url":"https:\/\/b24-ktafz3.bitrix24.ru\/rest\/profile.json","content_type":"application\/json; charset=utf-8","http_code":401,"header_size":786,"request_size":260,"filetime":-1,"ssl_verify_result":0,"redirect_count":0,"total_time":0.303216,"namelookup_time":0.124897,"connect_time":0.128481,"pretransfer_time":0.153507,"size_upload":75,"size_download":86,"speed_download":283,"speed_upload":247,"download_content_length":-1,"upload_content_length":75,"starttransfer_time":0.303184,"redirect_time":0,"redirect_url":"","primary_ip":"195.208.185.4","certinfo":[],"primary_port":443,"local_ip":"10.0.0.21","local_port":52632},"params":{"method":"profile","params":{"auth":"cf92486400634396006340ea0000000200000775fa5dfcbd3bfb5d61ccd0365e1e04c9"}},"result":{"result":{"ID":"2","ADMIN":true,"NAME":"\u0410\u043b\u0435\u043a\u0441\u0435\u0439","LAST_NAME":"","PERSONAL_GENDER":"","TIME_ZONE":"","TIME_ZONE_OFFSET":10800},"time":{"start":1682477821.51832,"finish":1682477821.655881,"duration":0.13756084442138672,"processing":0.001981019973754883,"date_start":"2023-04-26T05:57:01+03:00","date_finish":"2023-04-26T05:57:01+03:00","operating_reset_at":1682478421,"operating":0}}}